tux_mixer/__init__.py
tux_mixer/command_line.py
tux_mixer/control.py
tux_mixer/front.py
tux_mixer/pot.txt
tux_mixer/sleep.txt
tux_mixer/tux_mixer_logo_mini.png
tux_mixer-1.0.dist-info/LICENSE.txt
tux_mixer-1.0.dist-info/METADATA
tux_mixer-1.0.dist-info/WHEEL
tux_mixer-1.0.dist-info/entry_points.txt
tux_mixer-1.0.dist-info/top_level.txt
tux_mixer-1.0.dist-info/RECORD
