Metadata-Version: 2.1
Name: tux-mixer
Version: 1.0
Summary: PulseAudio control with potentiometers
Home-page: http://github.com/dogonso/tux_mixer
Author: Dogukan Meral
Author-email: dogukan.meral@yahoo.com
License: MIT
Keywords: mixer pulse audio tux volume control linux
Platform: UNKNOWN
Classifier: License :: OSI Approved :: MIT License
Classifier: Operating System :: POSIX :: Linux
Classifier: Programming Language :: Python :: 3.8
Classifier: Topic :: Multimedia :: Sound/Audio :: Mixers
Requires-Dist: notify2
Requires-Dist: pulsectl (==21.3.4)
Requires-Dist: pyfirmata
Requires-Dist: pystray
Requires-Dist: testresources
